api_key_rotator/__init__.py
api_key_rotator/rotator.py
api_key_rotator_lang1234-0.1.1.dist-info/licenses/LICENSE
api_key_rotator_lang1234-0.1.1.dist-info/METADATA
api_key_rotator_lang1234-0.1.1.dist-info/WHEEL
api_key_rotator_lang1234-0.1.1.dist-info/top_level.txt
api_key_rotator_lang1234-0.1.1.dist-info/RECORD
