Metadata-Version: 2.4
Name: api-key-rotator-lang1234
Version: 0.1.1
Summary: A Python library for rotating API keys with automatic expiration handling
Home-page: https://github.com/xLang1234/api-key-rotator
Author: xLang1234
License: MIT
Project-URL: Homepage, https://github.com/xLang1234/api-key-rotator
Project-URL: Documentation, https://github.com/xLang1234/api-key-rotator#readme
Project-URL: Repository, https://github.com/xLang1234/api-key-rotator
Project-URL: Bug Tracker, https://github.com/xLang1234/api-key-rotator/issues
Keywords: api,key,rotation,rate-limit,api-key,key-management,thread-safe
Classifier: Development Status :: 4 - Beta
Classifier: Intended Audience :: Developers
Classifier: Topic :: Software Development :: Libraries :: Python Modules
Classifier: License :: OSI Approved :: MIT License
Classifier: Programming Language :: Python :: 3
Classifier: Programming Language :: Python :: 3.7
Classifier: Programming Language :: Python :: 3.8
Classifier: Programming Language :: Python :: 3.9
Classifier: Programming Language :: Python :: 3.10
Classifier: Programming Language :: Python :: 3.11
Classifier: Programming Language :: Python :: 3.12
Classifier: Operating System :: OS Independent
Classifier: Typing :: Typed
Requires-Python: >=3.7
License-File: LICENSE
Dynamic: home-page
Dynamic: license-file
Dynamic: requires-python
